Workbook

Sheet Backlog
A1: ID | B1: Épopée | C1: Acteur | D1: User Story | E1: Priorité (MoSCoW) | F1: Sprint | G1: Story Points | H1: Critères d'acceptation
A2: US-001 | B2: Infrastructure & Setup | C2: Équipe technique | D2: Mettre en place le dépôt GitHub avec structure frontend (React) / backend (Django) séparée | E2: Must | F2: Sprint 0 | G2: 3 | H2: Dépôt créé avec README, .gitignore, branches main/develop, conventions de commit définies.
A3: US-002 | B3: Infrastructure & Setup | C3: Équipe technique | D3: Configurer les environnements dev / staging / production | E3: Must | F3: Sprint 0 | G3: 5 | H3: Variables d'environnement séparées ; accès restreint à la prod ; documentation de déploiement.
A4: US-003 | B4: Infrastructure & Setup | C4: Équipe technique | D4: Mettre en place la CI/CD (GitHub Actions : lint, tests, build) | E4: Must | F4: Sprint 0 | G4: 5 | H4: Pipeline exécuté à chaque push ; échec de build bloque la fusion sur develop.
A5: US-004 | B5: Infrastructure & Setup | C5: Équipe technique | D5: Configurer Docker / docker-compose (PostgreSQL, Redis) | E5: Must | F5: Sprint 0 | G5: 5 | H5: docker-compose up démarre l'environnement complet en local en une commande.
A6: US-005 | B6: Infrastructure & Setup | C6: Équipe technique | D6: Initialiser le projet Django + Django REST Framework | E6: Must | F6: Sprint 0 | G6: 3 | H6: Structure en apps modulaires ; admin Django accessible ; migrations initiales appliquées.
A7: US-006 | B7: Infrastructure & Setup | C7: Équipe technique | D7: Initialiser le projet React + Redux Toolkit + routing | E7: Must | F7: Sprint 0 | G7: 3 | H7: Arborescence de composants définie ; store Redux configuré ; build de production fonctionnel.
A8: US-007 | B8: Infrastructure & Setup | C8: Équipe technique | D8: Générer automatiquement la documentation API (Swagger/OpenAPI) | E8: Should | F8: Sprint 0 | G8: 3 | H8: Endpoint /docs affiche la spec interactive à jour avec le code.
A9: US-008 | B9: Infrastructure & Setup | C9: Équipe technique | D9: Mettre en place le monitoring des erreurs (Sentry) et les logs | E9: Should | F9: Sprint 0 | G9: 2 | H9: Toute exception non gérée en production remonte une alerte avec stack trace.
A10: US-009 | B10: Authentification & Profils | C10: Visiteur | D10: M'inscrire avec mon numéro de téléphone et un mot de passe | E10: Must | F10: Sprint 1 | G10: 5 | H10: Numéro unique vérifié par format E.164 ; mot de passe hashé (bcrypt) ; compte créé avec rôle 'utilisateur'.
A11: US-010 | B11: Authentification & Profils | C11: Utilisateur | D11: Me connecter avec vérification en deux étapes (2FA par SMS) | E11: Must | F11: Sprint 1 | G11: 8 | H11: Code OTP à 6 chiffres envoyé par SMS, expire après 5 min, JWT émis après validation.
A12: US-011 | B12: Authentification & Profils | C12: Utilisateur | D12: Modifier mon profil (nom, photo, email) | E12: Must | F12: Sprint 1 | G12: 3 | H12: Modifications persistées ; email revalidé si changé.
A13: US-012 | B13: Authentification & Profils | C13: Utilisateur | D13: Changer mon mot de passe | E13: Must | F13: Sprint 1 | G13: 2 | H13: Ancien mot de passe requis ; nouveau mot de passe ≥ 8 caractères.
... A66: US-065 | B66: QA & Déploiement | C66: Équipe technique | D66: Rédiger le manuel utilisateur par rôle | E66: Should | F66: Sprint 7 | G66: 5 | H66: Guides distincts pour acheteurs, vendeurs, livreurs, modérateurs, admins.

Sheet Sprints
A1: Sprint | B1: Durée | C1: Objectif | D1: Nb Stories | E1: Total Story Points | F1: Points "Must"
A2: Sprint 0 | B2: Semaine 1 | C2: Fondations techniques : repo, CI/CD, Docker, scaffolding back/front | D2: =COUNTIF(Backlog!F:F,A2) -> 8 | E2: =SUMIF(Backlog!F:F,A2,Backlog!G:G) -> 29 | F2: =SUMIFS(Backlog!G:G,Backlog!F:F,A2,Backlog!E:E,"Must") -> 24
A3: Sprint 1 | B3: Semaines 2-3 | C3: Authentification, 2FA, gestion de profils et rôles | D3: =COUNTIF(Backlog!F:F,A3) -> 8 | E3: =SUMIF(Backlog!F:F,A3,Backlog!G:G) -> 31 | F3: =SUMIFS(Backlog!G:G,Backlog!F:F,A3,Backlog!E:E,"Must") -> 29
A4: Sprint 2 | B4: Semaines 4-6 | C4: Catalogue : annonces, catégories, modération de publication | D4: =COUNTIF(Backlog!F:F,A4) -> 8 | E4: =SUMIF(Backlog!F:F,A4,Backlog!G:G) -> 38 | F4: =SUMIFS(Backlog!G:G,Backlog!F:F,A4,Backlog!E:E,"Must") -> 36
A5: Sprint 3 | B5: Semaines 7-9 | C5: Recherche, carte interactive, panier, commande, enchères | D5: =COUNTIF(Backlog!F:F,A5) -> 8 | E5: =SUMIF(Backlog!F:F,A5,Backlog!G:G) -> 45 | F5: =SUMIFS(Backlog!G:G,Backlog!F:F,A5,Backlog!E:E,"Must") -> 29
A6: Sprint 4 | B6: Semaines 10-12 | C6: Paiement Mobile Money / COD, interface livreur, QR code | D6: =COUNTIF(Backlog!F:F,A6) -> 7 | E6: =SUMIF(Backlog!F:F,A6,Backlog!G:G) -> 41 | F6: =SUMIFS(Backlog!G:G,Backlog!F:F,A6,Backlog!E:E,"Must") -> 34
A7: Sprint 5 | B7: Semaines 13-14 | C7: Avis, réputation, follow, parrainage, alertes, badges | D7: =COUNTIF(Backlog!F:F,A7) -> 8 | E7: =SUMIF(Backlog!F:F,A7,Backlog!G:G) -> 33 | F7: =SUMIFS(Backlog!G:G,Backlog!F:F,A7,Backlog!E:E,"Must") -> 5
A8: Sprint 6 | B8: Semaines 15-16 | C8: Vendeur Pro (boutique, import CSV, stats) et modération | D8: =COUNTIF(Backlog!F:F,A8) -> 8 | E8: =SUMIF(Backlog!F:F,A8,Backlog!G:G) -> 40 | F8: =SUMIFS(Backlog!G:G,Backlog!F:F,A8,Backlog!E:E,"Must") -> 29
A9: Sprint 7 | B9: Semaines 17-18 | C9: Administration, QA, documentation et déploiement du MVP | D9: =COUNTIF(Backlog!F:F,A9) -> 10 | E9: =SUMIF(Backlog!F:F,A9,Backlog!G:G) -> 46 | F9: =SUMIFS(Backlog!G:G,Backlog!F:F,A9,Backlog!E:E,"Must") -> 26
C10: TOTAL | D10: =SUM(D2:D9) -> 65 | E10: =SUM(E2:E9) -> 303 | F10: =SUM(F2:F9) -> 212

Sheet Légende
A1: Méthode de priorisation MoSCoW
A3: Must | B3: Indispensable au lancement du MVP. Sans cette fonctionnalité, le produit n'a pas de valeur.
A5: Should | B5: Important mais non bloquant pour le lancement ; à livrer si le temps le permet.
A7: Could | B7: Souhaitable, améliore l'expérience mais reportable après le MVP.
A9: Won't | B9: Explicitement hors périmètre de cette version (à réévaluer plus tard).
A12: Story Points
A14: Échelle | B14: Suite de Fibonacci : 1, 2, 3, 5, 8, 13 (complexité relative, pas une durée en heures).
A17: Notes de planification
A19: • | B19: MVP visé en 4 mois, découpé en 8 sprints de 1 à 3 semaines (Sprint 0 = fondations techniques).
A21: • | B21: La feuille "Sprints" calcule automatiquement le nombre de stories et les points par sprint (formules liées à la feuille Backlog).
A23: • | B23: Cette répartition est un point de départ : à ajuster après l'estimation collective de l'équipe (planning poker).
